greengo/__init__.py
greengo/greengo.py
greengo-1.0.6.dist-info/LICENSE.txt
greengo-1.0.6.dist-info/METADATA
greengo-1.0.6.dist-info/WHEEL
greengo-1.0.6.dist-info/entry_points.txt
greengo-1.0.6.dist-info/top_level.txt
greengo-1.0.6.dist-info/RECORD
