Metadata-Version: 2.1
Name: greengo
Version: 1.0.6
Summary: AWS Greengrass file-based setup tool
Home-page: http://github.com/dzimine/greengo
Author: Dmitri Zimine
Author-email: dz_removethis@stackstorm.com
License: MIT
Keywords: AWS,IoT,Greengrass,Lambda
Platform: UNKNOWN
Requires-Dist: fire
Requires-Dist: boto3
Requires-Dist: botocore
Requires-Dist: pyyaml
